[
  {
    "name": "Jean-Philippe Baconnais",
    "agency": "Nantes, FR",
    "github": {
      "handle": "jeanphibaconnais"
    },
    "gitlab": {
      "handle": "jeanphi-baconnais"
    }
  },
  {
    "name": "Alex Palma",
    "agency": "Brest, FR",
    "github": {
      "handle": "elya29"
    },
    "gitlab": {}
  },
  {
    "name": "Jonathan Lagneaux",
    "agency": "Brest, FR",
    "github": {
      "handle": "Gosunet"
    },
    "gitlab": {}
  },
  {
    "name": "Glenn Guegan",
    "agency": "Brest, FR",
    "github": {
      "handle": "GlennGuegan"
    },
    "gitlab": {
      "handle": "minicrash"
    }
  },
  {
    "name": "Antoine Duchenet",
    "agency": "Brest, FR",
    "github": {
      "handle": "antoine-duchenet"
    },
    "gitlab": {
      "handle": "antoine-duchenet"
    }
  }
]
